layer7_utilities/__init__.py
layer7_utilities/auth/__init__.py
layer7_utilities/auth/base_Auth.py
layer7_utilities/database/__init__.py
layer7_utilities/database/database.py
layer7_utilities/exceptions/__init__.py
layer7_utilities/exceptions/exceptions.py
layer7_utilities/logger/Logger.py
layer7_utilities/logger/__init__.py
layer7_utilities/logger/logging_config.json
Layer_7_Utilities-1.3.0.dist-info/LICENSE.txt
Layer_7_Utilities-1.3.0.dist-info/METADATA
Layer_7_Utilities-1.3.0.dist-info/WHEEL
Layer_7_Utilities-1.3.0.dist-info/top_level.txt
Layer_7_Utilities-1.3.0.dist-info/RECORD
