Metadata-Version: 2.1
Name: Layer-7-Utilities
Version: 1.3.0
Summary: This is a set of utilities used by https://Layer7.Solutions for the software tools we create. It includes a logger with default configuration information we setup as well as an oAuth wrapper to be able to pull login information from a custom database.
Home-page: https://Layer7.Solutions
Author: Layer 7 Solutions (Mike Wohlrab)
Author-email: Mike@Layer7.Solutions
License: MIT
Platform: UNKNOWN
Classifier: Programming Language :: Python :: 3
Classifier: License :: OSI Approved :: MIT License
Classifier: Operating System :: OS Independent
Classifier: Intended Audience :: Developers
Requires-Dist: psycopg2 (>=2.7.7)
Requires-Dist: sentry-sdk (>=0.7.0)
Requires-Dist: praw (>=6.1.1)
